.gitignore
README.md
setup.py
hyphenation/__init__.py
hyphenation/core.py
hyphenation.egg-info/PKG-INFO
hyphenation.egg-info/SOURCES.txt
hyphenation.egg-info/dependency_links.txt
hyphenation.egg-info/not-zip-safe
hyphenation.egg-info/requires.txt
hyphenation.egg-info/top_level.txt
hyphenation/rules/README
hyphenation/rules/hyph_as_IN.dic
hyphenation/rules/hyph_bn_IN.dic
hyphenation/rules/hyph_en_US.dic
hyphenation/rules/hyph_gu_IN.dic
hyphenation/rules/hyph_hi_IN.dic
hyphenation/rules/hyph_kn_IN.dic
hyphenation/rules/hyph_ml_IN.dic
hyphenation/rules/hyph_mr_IN.dic
hyphenation/rules/hyph_or_IN.dic
hyphenation/rules/hyph_pa_IN.dic
hyphenation/rules/hyph_ta_IN.dic
hyphenation/rules/hyph_te_IN.dic
hyphenation/templates/hyphenation.html