Metadata-Version: 1.0
Name: hyphenation
Version: 2.0
Summary: Hyphenation module for Python
Home-page: http://gitorious.org/hyphenator
Author: Santhosh Thottingal
Author-email: santhosh.thottingal@gmail.com
License: LGLP 3.0
Platform: UNKNOWN
